{ "color": 12632256.0, "persistent": 1.0, "text": "Point\nRanking\nCreator", "release_duration": 0.0, "queueable": 0.0, "command_list": [ { "cmd": 4.0, "obsid": "Main", "pos": 0.0, "vis": 1.0, "ms": 0.0, "sel": 0.0, "dis": 0.0, "xpan": 0.0, "b0": "初期化系", "v0": 28.0 }, { "cmd": 78.0, "obsid": "Main", "pos": 1.0, "vis": 1.0, "ms": 0.0, "sel": 0.0, "dis": 0.0, "xpan": 0.0, "b0": "tmpArray" }, { "cmd": 17.0, "obsid": "Main", "pos": 2.0, "vis": 1.0, "ms": 0.0, "sel": 0.0, "dis": 0.0, "xpan": 0.0, "b0": "tmpArray" }, { "b1": "basic", "b3": "debug", "cmd": 125.0, "obsid": "Main", "pos": 3.0, "vis": 1.0, "ms": 0.0, "sel": 0.0, "dis": 0.0, "xpan": 0.0, "b0": "\/IPS\/ips.ini", "b2": "debug" }, { "b1": "basic", "b3": "channel", "cmd": 127.0, "obsid": "Main", "pos": 4.0, "vis": 1.0, "ms": 0.0, "sel": 0.0, "dis": 0.0, "xpan": 0.0, "b0": "\/IPS\/ips.ini", "b2": "channel" }, { "b1": "pointCsvPath", "cmd": 163.0, "obsid": "Main", "pos": 5.0, "vis": 1.0, "ms": 0.0, "sel": 0.0, "dis": 0.0, "xpan": 0.0, "b0": "main_directory" }, { "b1": "rankingCsvPath", "cmd": 163.0, "obsid": "Main", "pos": 6.0, "vis": 1.0, "ms": 0.0, "sel": 0.0, "dis": 0.0, "xpan": 0.0, "b0": "main_directory" }, { "b1": "debugLogCsvPath", "cmd": 163.0, "obsid": "Main", "pos": 7.0, "vis": 1.0, "ms": 0.0, "sel": 0.0, "dis": 0.0, "xpan": 0.0, "b0": "main_directory" }, { "b1": "+=", "cmd": 15.0, "obsid": "Main", "pos": 8.0, "vis": 1.0, "ms": 0.0, "sel": 0.0, "dis": 0.0, "xpan": 0.0, "b0": "pointCsvPath", "b2": "\"IPS\\points.csv\"" }, { "b1": "+=", "cmd": 15.0, "obsid": "Main", "pos": 9.0, "vis": 1.0, "ms": 0.0, "sel": 0.0, "dis": 0.0, "xpan": 0.0, "b0": "rankingCsvPath", "b2": "\"IPS\\ranking.csv\"" }, { "b1": "+=", "cmd": 15.0, "obsid": "Main", "pos": 10.0, "vis": 1.0, "ms": 0.0, "sel": 0.0, "dis": 0.0, "xpan": 0.0, "b0": "debugLogCsvPath", "b2": "\"IPS\\debuglog.csv\"" }, { "cmd": 211.0, "obsid": "Main", "pos": 11.0, "vis": 1.0, "ms": 0.0, "sel": 0.0, "dis": 0.0, "xpan": 0.0, "b0": "point" }, { "cmd": 211.0, "obsid": "Main", "pos": 12.0, "vis": 1.0, "ms": 0.0, "sel": 0.0, "dis": 0.0, "xpan": 0.0, "b0": "ranking" }, { "cmd": 211.0, "obsid": "Main", "pos": 13.0, "vis": 1.0, "ms": 0.0, "sel": 0.0, "dis": 0.0, "xpan": 0.0, "b0": "debugLog" }, { "b1": "\/$pointCsvPath$\/", "cmd": 202.0, "obsid": "Main", "pos": 14.0, "vis": 1.0, "ms": 0.0, "sel": 0.0, "dis": 0.0, "xpan": 0.0, "b0": "point" }, { "b1": "\/$rankingCsvPath$\/", "cmd": 202.0, "obsid": "Main", "pos": 15.0, "vis": 1.0, "ms": 0.0, "sel": 0.0, "dis": 0.0, "xpan": 0.0, "b0": "ranking" }, { "b1": "\/$debugLogCsvPath$\/", "cmd": 202.0, "obsid": "Main", "pos": 16.0, "vis": 1.0, "ms": 0.0, "sel": 0.0, "dis": 0.0, "xpan": 0.0, "b0": "debugLog" }, { "b53": "", "b5": "", "b13": "==", "v14": 0.0, "b36": "", "b38": "", "v10": 0.0, "b32": "", "b19": "==", "b57": "", "b59": "", "b17": "", "b1": "==", "v18": 0.0, "v16": 0.0, "b34": "==", "b7": "==", "b11": "", "b9": "", "b51": "", "b15": "", "b3": "", "b55": "==", "v12": 0.0, "cmd": 7.0, "b30": "", "b43": "==", "v21": 0.0, "v1": 0.0, "b26": "", "b28": "==", "obsid": "Main", "b22": "==", "pos": 17.0, "v5": 0.0, "b47": "", "b49": "==", "v3": 0.0, "vis": 1.0, "b24": "", "ms": 0.0, "b41": "", "sel": 0.0, "b45": "", "v9": 0.0, "dis": 0.0, "xpan": 0.0, "b20": "", "v7": 0.0, "b33": "", "v11": 0.0, "b16": "==", "b0": "debug", "b58": "==", "b56": "", "b18": "", "b4": "==", "b12": "", "b52": "==", "b39": "", "b37": "==", "v15": 0.0, "b54": "", "b14": "", "b2": "1", "b31": "==", "v13": 0.0, "b35": "", "v17": 0.0, "v19": 0.0, "b50": "", "b8": "", "b6": "", "b10": "==", "b23": "", "v4": 0.0, "b48": "", "b46": "==", "v20": 0.0, "b42": "", "b29": "", "v0": 2.0, "b27": "", "b44": "", "b21": "", "v6": 0.0, "v8": 0.0, "v2": 1.0, "b25": "==", "b40": "==", "v22": 0.0 }, { "b1": "[PRC]<\/$global.since_2020$\/ \/$global.elapsed_time$\/> PROCESS START.", "cmd": 200.0, "obsid": "Main", "pos": 18.0, "vis": 1.0, "ms": 0.0, "sel": 0.0, "dis": 0.0, "xpan": 0.0, "b0": "debugLog" }, { "b1": "\/$debugLogCsvPath$\/", "cmd": 201.0, "obsid": "Main", "pos": 19.0, "vis": 1.0, "ms": 0.0, "sel": 0.0, "dis": 0.0, "xpan": 0.0, "b0": "debugLog" }, { "cmd": 6.0, "obsid": "Main", "pos": 20.0, "vis": 1.0, "ms": 0.0, "sel": 0.0, "dis": 0.0, "xpan": 0.0, "b0": "ポイント降順でソート", "v0": 2.0 }, { "b1": "\"point\"", "cmd": 205.0, "v1": true, "obsid": "Main", "pos": 21.0, "vis": 1.0, "ms": 0.0, "sel": 0.0, "dis": 0.0, "xpan": 0.0, "b0": "point", "v0": false }, { "b1": "\/$pointCsvPath$\/", "cmd": 201.0, "obsid": "Main", "pos": 22.0, "vis": 1.0, "ms": 0.0, "sel": 0.0, "dis": 0.0, "xpan": 0.0, "b0": "point" }, { "b1": "rows", "cmd": 216.0, "obsid": "Main", "pos": 23.0, "vis": 1.0, "ms": 0.0, "sel": 0.0, "dis": 0.0, "xpan": 0.0, "b0": "point", "v0": 0.0 }, { "b1": "=", "cmd": 15.0, "obsid": "Main", "pos": 24.0, "vis": 1.0, "ms": 0.0, "sel": 0.0, "dis": 0.0, "xpan": 0.0, "b0": "r", "b2": "0" }, { "b1": "=", "cmd": 15.0, "obsid": "Main", "pos": 25.0, "vis": 1.0, "ms": 0.0, "sel": 0.0, "dis": 0.0, "xpan": 0.0, "b0": "previous", "b2": "99999999" }, { "b53": "", "b5": "", "b13": "==", "v14": 0.0, "b36": "", "b38": "", "v10": 0.0, "b32": "", "b19": "==", "b57": "", "b59": "", "b17": "", "b1": "==", "v18": 0.0, "v16": 0.0, "b34": "==", "b7": "==", "b11": "", "b9": "", "b51": "", "b15": "", "b3": "", "b55": "==", "v12": 0.0, "cmd": 7.0, "b30": "", "b43": "==", "v21": 0.0, "v1": 0.0, "b26": "", "b28": "==", "obsid": "Main", "b22": "==", "pos": 26.0, "v5": 0.0, "b47": "", "b49": "==", "v3": 0.0, "vis": 1.0, "b24": "", "ms": 0.0, "b41": "", "sel": 0.0, "b45": "", "v9": 0.0, "dis": 0.0, "xpan": 0.0, "b20": "", "v7": 0.0, "b33": "", "v11": 0.0, "b16": "==", "b0": "debug", "b58": "==", "b56": "", "b18": "", "b4": "==", "b12": "", "b52": "==", "b39": "", "b37": "==", "v15": 0.0, "b54": "", "b14": "", "b2": "1", "b31": "==", "v13": 0.0, "b35": "", "v17": 0.0, "v19": 0.0, "b50": "", "b8": "", "b6": "", "b10": "==", "b23": "", "v4": 0.0, "b48": "", "b46": "==", "v20": 0.0, "b42": "", "b29": "", "v0": 2.0, "b27": "", "b44": "", "b21": "", "v6": 0.0, "v8": 0.0, "v2": 1.0, "b25": "==", "b40": "==", "v22": 0.0 }, { "b1": "[PRC]<\/$global.since_2020$\/ \/$global.elapsed_time$\/> rows=\/$rows$\/", "cmd": 200.0, "obsid": "Main", "pos": 27.0, "vis": 1.0, "ms": 0.0, "sel": 0.0, "dis": 0.0, "xpan": 0.0, "b0": "debugLog" }, { "b1": "\/$debugLogCsvPath$\/", "cmd": 201.0, "obsid": "Main", "pos": 28.0, "vis": 1.0, "ms": 0.0, "sel": 0.0, "dis": 0.0, "xpan": 0.0, "b0": "debugLog" }, { "cmd": 6.0, "obsid": "Main", "pos": 29.0, "vis": 1.0, "ms": 0.0, "sel": 0.0, "dis": 0.0, "xpan": 0.0, "b0": "ランキングCSVを作成(毎回新規作成)", "v0": 7.0 }, { "b1": "rankingRows", "cmd": 216.0, "obsid": "Main", "pos": 30.0, "vis": 1.0, "ms": 0.0, "sel": 0.0, "dis": 1.0, "xpan": 0.0, "b0": "ranking", "v0": 0.0 }, { "b1": "rankingRows", "cmd": 81.0, "obsid": "Main", "pos": 31.0, "vis": 1.0, "ms": 0.0, "sel": 0.0, "dis": 1.0, "xpan": 0.0, "b0": "typeOfRankingRows" }, { "cmd": 141.0, "obsid": "Main", "pos": 32.0, "vis": 1.0, "ms": 0.0, "sel": 0.0, "dis": 1.0, "xpan": 0.0, "b0": "\/$typeOfRankingRows$\/", "v0": false }, { "b1": "row", "cmd": 198.0, "obsid": "Main", "pos": 33.0, "vis": 1.0, "ms": 0.0, "sel": 0.0, "dis": 0.0, "xpan": 0.0, "b0": "ranking" }, { "b5": "display_name", "b1": "rank", "b3": "point", "cmd": 199.0, "obsid": "Main", "pos": 34.0, "vis": 1.0, "ms": 0.0, "sel": 0.0, "dis": 0.0, "xpan": 0.0, "b0": "ranking", "b4": "0", "b2": "0", "b6": "Dummy" }, { "b5": "", "b1": "user_name", "b3": "", "cmd": 199.0, "obsid": "Main", "pos": 35.0, "vis": 1.0, "ms": 0.0, "sel": 0.0, "dis": 0.0, "xpan": 0.0, "b0": "ranking", "b4": "", "b2": "Dummy", "b6": "" }, { "b1": "\/$rankingCsvPath$\/", "cmd": 201.0, "obsid": "Main", "pos": 36.0, "vis": 1.0, "ms": 0.0, "sel": 0.0, "dis": 0.0, "xpan": 0.0, "b0": "ranking" }, { "cmd": 4.0, "obsid": "Main", "pos": 37.0, "vis": 1.0, "ms": 0.0, "sel": 0.0, "dis": 0.0, "xpan": 0.0, "b0": "処理にかかるおおよその時間を表示する", "v0": 2.0 }, { "b1": "=", "cmd": 15.0, "obsid": "Main", "pos": 38.0, "vis": 1.0, "ms": 0.0, "sel": 0.0, "dis": 0.0, "xpan": 0.0, "b0": "seconds", "b2": "(rows * 2)" }, { "cmd": 141.0, "obsid": "Main", "pos": 39.0, "vis": 1.0, "ms": 0.0, "sel": 0.0, "dis": 0.0, "xpan": 0.0, "b0": "Please wait for about \/$seconds$\/ sec.", "v0": false }, { "cmd": 5.0, "obsid": "Main", "pos": 40.0, "vis": 1.0, "ms": 0.0, "sel": 0.0, "dis": 0.0, "xpan": 0.0, "b0": "ランキング生成処理", "v0": 45.0 }, { "cmd": 9.0, "obsid": "Main", "pos": 41.0, "vis": 1.0, "ms": 0.0, "sel": 0.0, "dis": 0.0, "xpan": 0.0, "b0": "rows", "v0": 21.0 }, { "b1": "\"user_id\"", "b3": "userId", "cmd": 206.0, "obsid": "Main", "pos": 42.0, "vis": 1.0, "ms": 0.0, "sel": 0.0, "dis": 0.0, "xpan": 0.0, "b0": "point", "b2": "r" }, { "b1": "\"point\"", "b3": "point", "cmd": 206.0, "obsid": "Main", "pos": 43.0, "vis": 1.0, "ms": 0.0, "sel": 0.0, "dis": 0.0, "xpan": 0.0, "b0": "point", "b2": "r" }, { "b1": "point", "cmd": 79.0, "obsid": "Main", "pos": 44.0, "vis": 1.0, "ms": 0.0, "sel": 0.0, "dis": 0.0, "xpan": 0.0, "b0": "point" }, { "b53": "", "b5": "", "b13": "==", "v14": 0.0, "b36": "", "b38": "", "v10": 0.0, "b32": "", "b19": "==", "b57": "", "b59": "", "b17": "", "b1": "==", "v18": 0.0, "v16": 0.0, "b34": "==", "b7": "==", "b11": "", "b9": "", "b51": "", "b15": "", "b3": "", "b55": "==", "v12": 0.0, "cmd": 7.0, "b30": "", "b43": "==", "v21": 0.0, "v1": 0.0, "b26": "", "b28": "==", "obsid": "Main", "b22": "==", "pos": 45.0, "v5": 0.0, "b47": "", "b49": "==", "v3": 0.0, "vis": 1.0, "b24": "", "ms": 0.0, "b41": "", "sel": 0.0, "b45": "", "v9": 0.0, "dis": 0.0, "xpan": 0.0, "b20": "", "v7": 0.0, "b33": "", "v11": 0.0, "b16": "==", "b0": "debug", "b58": "==", "b56": "", "b18": "", "b4": "==", "b12": "", "b52": "==", "b39": "", "b37": "==", "v15": 0.0, "b54": "", "b14": "", "b2": "1", "b31": "==", "v13": 0.0, "b35": "", "v17": 0.0, "v19": 0.0, "b50": "", "b8": "", "b6": "", "b10": "==", "b23": "", "v4": 0.0, "b48": "", "b46": "==", "v20": 0.0, "b42": "", "b29": "", "v0": 2.0, "b27": "", "b44": "", "b21": "", "v6": 0.0, "v8": 0.0, "v2": 1.0, "b25": "==", "b40": "==", "v22": 0.0 }, { "b1": "[PRC]<\/$global.since_2020$\/ \/$global.elapsed_time$\/> id=\/$userId$\/; point=\/$point$\/", "cmd": 200.0, "obsid": "Main", "pos": 46.0, "vis": 1.0, "ms": 0.0, "sel": 0.0, "dis": 0.0, "xpan": 0.0, "b0": "debugLog" }, { "b1": "\/$debugLogCsvPath$\/", "cmd": 201.0, "obsid": "Main", "pos": 47.0, "vis": 1.0, "ms": 0.0, "sel": 0.0, "dis": 0.0, "xpan": 0.0, "b0": "debugLog" }, { "b1": "\/$userId$\/", "cmd": 171.0, "obsid": "Main", "pos": 48.0, "vis": 1.0, "ms": 0.0, "sel": 0.0, "dis": 0.0, "xpan": 0.0, "b0": "", "b2": "userInfo" }, { "cmd": 190.0, "obsid": "Main", "pos": 49.0, "vis": 1.0, "ms": 0.0, "sel": 0.0, "dis": 0.0, "xpan": 0.0, "b0": "2000" }, { "b1": "login", "cmd": 164.0, "obsid": "Main", "pos": 50.0, "vis": 1.0, "ms": 0.0, "sel": 0.0, "dis": 0.0, "xpan": 0.0, "b0": "userInfo", "b2": "userName" }, { "b1": "display_name", "cmd": 164.0, "obsid": "Main", "pos": 51.0, "vis": 1.0, "ms": 0.0, "sel": 0.0, "dis": 0.0, "xpan": 0.0, "b0": "userInfo", "b2": "displayName" }, { "cmd": 4.0, "obsid": "Main", "pos": 52.0, "vis": 1.0, "ms": 0.0, "sel": 0.0, "dis": 0.0, "xpan": 0.0, "b0": "自分自信はランキングから除外する", "v0": 9.0 }, { "b53": "", "b5": "", "b13": "==", "v14": 0.0, "b36": "", "b38": "", "v10": 0.0, "b32": "", "b19": "==", "b57": "", "b59": "", "b17": "", "b1": "==", "v18": 0.0, "v16": 0.0, "b34": "==", "b7": "==", "b11": "", "b9": "", "b51": "", "b15": "", "b3": "", "b55": "==", "v12": 0.0, "cmd": 7.0, "b30": "", "b43": "==", "v21": 0.0, "v1": 8.0, "b26": "", "b28": "==", "obsid": "Main", "b22": "==", "pos": 53.0, "v5": 0.0, "b47": "", "b49": "==", "v3": 0.0, "vis": 1.0, "b24": "", "ms": 0.0, "b41": "", "sel": 0.0, "b45": "", "v9": 0.0, "dis": 0.0, "xpan": 0.0, "b20": "", "v7": 0.0, "b33": "", "v11": 0.0, "b16": "==", "b0": "userName", "b58": "==", "b56": "", "b18": "", "b4": "==", "b12": "", "b52": "==", "b39": "", "b37": "==", "v15": 0.0, "b54": "", "b14": "", "b2": "channel", "b31": "==", "v13": 0.0, "b35": "", "v17": 0.0, "v19": 0.0, "b50": "", "b8": "", "b6": "", "b10": "==", "b23": "", "v4": 0.0, "b48": "", "b46": "==", "v20": 0.0, "b42": "", "b29": "", "v0": 0.0, "b27": "", "b44": "", "b21": "", "v6": 0.0, "v8": 0.0, "v2": 1.0, "b25": "==", "b40": "==", "v22": 0.0 }, { "cmd": 6.0, "obsid": "Main", "pos": 54.0, "vis": 1.0, "ms": 0.0, "sel": 0.0, "dis": 0.0, "xpan": 0.0, "b0": "オブジェクトを生成してstringifyしたうえで配列に突っ込む", "v0": 7.0 }, { "cmd": 16.0, "obsid": "Main", "pos": 55.0, "vis": 1.0, "ms": 0.0, "sel": 0.0, "dis": 0.0, "xpan": 0.0, "b0": "tmpObj" }, { "b1": "userId", "cmd": 165.0, "obsid": "Main", "pos": 56.0, "vis": 1.0, "ms": 0.0, "sel": 0.0, "dis": 0.0, "xpan": 0.0, "b0": "tmpObj", "b2": "userId" }, { "b1": "userName", "cmd": 165.0, "obsid": "Main", "pos": 57.0, "vis": 1.0, "ms": 0.0, "sel": 0.0, "dis": 0.0, "xpan": 0.0, "b0": "tmpObj", "b2": "userName" }, { "b1": "displayName", "cmd": 165.0, "obsid": "Main", "pos": 58.0, "vis": 1.0, "ms": 0.0, "sel": 0.0, "dis": 0.0, "xpan": 0.0, "b0": "tmpObj", "b2": "displayName" }, { "b1": "point", "cmd": 165.0, "obsid": "Main", "pos": 59.0, "vis": 1.0, "ms": 0.0, "sel": 0.0, "dis": 0.0, "xpan": 0.0, "b0": "tmpObj", "b2": "point" }, { "b1": "tmpObj", "cmd": 18.0, "obsid": "Main", "pos": 60.0, "vis": 1.0, "ms": 0.0, "sel": 0.0, "dis": 0.0, "xpan": 0.0, "b0": "tmpStr" }, { "b1": "top", "cmd": 96.0, "obsid": "Main", "pos": 61.0, "vis": 1.0, "ms": 0.0, "sel": 0.0, "dis": 0.0, "xpan": 0.0, "b0": "tmpArray", "b2": "tmpStr" }, { "b1": "+=", "cmd": 15.0, "obsid": "Main", "pos": 62.0, "vis": 1.0, "ms": 0.0, "sel": 0.0, "dis": 0.0, "xpan": 0.0, "b0": "r", "b2": "1" }, { "b53": "", "b5": "", "b13": "==", "v14": 0.0, "b36": "", "b38": "", "v10": 0.0, "b32": "", "b19": "==", "b57": "", "b59": "", "b17": "", "b1": "==", "v18": 0.0, "v16": 0.0, "b34": "==", "b7": "==", "b11": "", "b9": "", "b51": "", "b15": "", "b3": "", "b55": "==", "v12": 0.0, "cmd": 7.0, "b30": "", "b43": "==", "v21": 0.0, "v1": 0.0, "b26": "", "b28": "==", "obsid": "Main", "b22": "==", "pos": 63.0, "v5": 0.0, "b47": "", "b49": "==", "v3": 0.0, "vis": 1.0, "b24": "", "ms": 0.0, "b41": "", "sel": 0.0, "b45": "", "v9": 0.0, "dis": 0.0, "xpan": 0.0, "b20": "", "v7": 0.0, "b33": "", "v11": 0.0, "b16": "==", "b0": "debug", "b58": "==", "b56": "", "b18": "", "b4": "==", "b12": "", "b52": "==", "b39": "", "b37": "==", "v15": 0.0, "b54": "", "b14": "", "b2": "1", "b31": "==", "v13": 0.0, "b35": "", "v17": 0.0, "v19": 0.0, "b50": "", "b8": "", "b6": "", "b10": "==", "b23": "", "v4": 0.0, "b48": "", "b46": "==", "v20": 0.0, "b42": "", "b29": "", "v0": 2.0, "b27": "", "b44": "", "b21": "", "v6": 0.0, "v8": 0.0, "v2": 1.0, "b25": "==", "b40": "==", "v22": 0.0 }, { "b1": "[PRC]<\/$global.since_2020$\/ \/$global.elapsed_time$\/> id=\/$userId$\/; point=\/$point$\/", "cmd": 200.0, "obsid": "Main", "pos": 64.0, "vis": 1.0, "ms": 0.0, "sel": 0.0, "dis": 0.0, "xpan": 0.0, "b0": "debugLog" }, { "b1": "\/$debugLogCsvPath$\/", "cmd": 201.0, "obsid": "Main", "pos": 65.0, "vis": 1.0, "ms": 0.0, "sel": 0.0, "dis": 0.0, "xpan": 0.0, "b0": "debugLog" }, { "b1": "rows", "cmd": 100.0, "obsid": "Main", "pos": 66.0, "vis": 1.0, "ms": 0.0, "sel": 0.0, "dis": 0.0, "xpan": 0.0, "b0": "tmpArray" }, { "b1": "=", "cmd": 15.0, "obsid": "Main", "pos": 67.0, "vis": 1.0, "ms": 0.0, "sel": 0.0, "dis": 0.0, "xpan": 0.0, "b0": "r", "b2": "0" }, { "cmd": 9.0, "obsid": "Main", "pos": 68.0, "vis": 1.0, "ms": 0.0, "sel": 0.0, "dis": 0.0, "xpan": 0.0, "b0": "rows", "v0": 16.0 }, { "cmd": 6.0, "obsid": "Main", "pos": 69.0, "vis": 1.0, "ms": 0.0, "sel": 0.0, "dis": 0.0, "xpan": 0.0, "b0": "ランキングCSVに書き込み", "v0": 13.0 }, { "b1": "0", "cmd": 98.0, "obsid": "Main", "pos": 70.0, "vis": 1.0, "ms": 0.0, "sel": 0.0, "dis": 0.0, "xpan": 0.0, "b0": "tmpArray", "b2": "tmpStr" }, { "b1": "\/$tmpStr$\/", "cmd": 168.0, "obsid": "Main", "pos": 71.0, "vis": 1.0, "ms": 0.0, "sel": 0.0, "dis": 0.0, "xpan": 0.0, "b0": "currentObj" }, { "b1": "point", "cmd": 164.0, "obsid": "Main", "pos": 72.0, "vis": 1.0, "ms": 0.0, "sel": 0.0, "dis": 0.0, "xpan": 0.0, "b0": "currentObj", "b2": "point" }, { "b1": "userName", "cmd": 164.0, "obsid": "Main", "pos": 73.0, "vis": 1.0, "ms": 0.0, "sel": 0.0, "dis": 0.0, "xpan": 0.0, "b0": "currentObj", "b2": "userName" }, { "b1": "displayName", "cmd": 164.0, "obsid": "Main", "pos": 74.0, "vis": 1.0, "ms": 0.0, "sel": 0.0, "dis": 0.0, "xpan": 0.0, "b0": "currentObj", "b2": "displayName" }, { "b53": "", "b5": "", "b13": "==", "v14": 0.0, "b36": "", "b38": "", "v10": 0.0, "b32": "", "b19": "==", "b57": "", "b59": "", "b17": "", "b1": "<", "v18": 0.0, "v16": 0.0, "b34": "==", "b7": "==", "b11": "", "b9": "", "b51": "", "b15": "", "b3": "", "b55": "==", "v12": 0.0, "cmd": 7.0, "b30": "", "b43": "==", "v21": 0.0, "v1": 0.0, "b26": "", "b28": "==", "obsid": "Main", "b22": "==", "pos": 75.0, "v5": 0.0, "b47": "", "b49": "==", "v3": 0.0, "vis": 1.0, "b24": "", "ms": 0.0, "b41": "", "sel": 0.0, "b45": "", "v9": 0.0, "dis": 0.0, "xpan": 0.0, "b20": "", "v7": 0.0, "b33": "", "v11": 0.0, "b16": "==", "b0": "point", "b58": "==", "b56": "", "b18": "", "b4": "==", "b12": "", "b52": "==", "b39": "", "b37": "==", "v15": 0.0, "b54": "", "b14": "", "b2": "previous", "b31": "==", "v13": 0.0, "b35": "", "v17": 0.0, "v19": 0.0, "b50": "", "b8": "", "b6": "", "b10": "==", "b23": "", "v4": 0.0, "b48": "", "b46": "==", "v20": 0.0, "b42": "", "b29": "", "v0": 1.0, "b27": "", "b44": "", "b21": "", "v6": 0.0, "v8": 0.0, "v2": 1.0, "b25": "==", "b40": "==", "v22": 0.0 }, { "b1": "=", "cmd": 15.0, "obsid": "Main", "pos": 76.0, "vis": 1.0, "ms": 0.0, "sel": 0.0, "dis": 0.0, "xpan": 0.0, "b0": "rank", "b2": "(r + 1)" }, { "b1": "=", "cmd": 15.0, "obsid": "Main", "pos": 77.0, "vis": 1.0, "ms": 0.0, "sel": 0.0, "dis": 0.0, "xpan": 0.0, "b0": "key", "b2": "(r + 1)" }, { "b1": "\/$key$\/", "cmd": 200.0, "obsid": "Main", "pos": 78.0, "vis": 1.0, "ms": 0.0, "sel": 0.0, "dis": 0.0, "xpan": 0.0, "b0": "ranking" }, { "b1": "\"rank\"", "b3": "=", "cmd": 207.0, "obsid": "Main", "pos": 79.0, "vis": 1.0, "ms": 0.0, "sel": 0.0, "dis": 0.0, "xpan": 0.0, "b0": "ranking", "b4": "rank", "b2": "r" }, { "b1": "\"point\"", "b3": "=", "cmd": 207.0, "obsid": "Main", "pos": 80.0, "vis": 1.0, "ms": 0.0, "sel": 0.0, "dis": 0.0, "xpan": 0.0, "b0": "ranking", "b4": "point", "b2": "r" }, { "b1": "\"display_name\"", "b3": "=", "cmd": 207.0, "obsid": "Main", "pos": 81.0, "vis": 1.0, "ms": 0.0, "sel": 0.0, "dis": 0.0, "xpan": 0.0, "b0": "ranking", "b4": "displayName", "b2": "r" }, { "b1": "\"user_name\"", "b3": "=", "cmd": 207.0, "obsid": "Main", "pos": 82.0, "vis": 1.0, "ms": 0.0, "sel": 0.0, "dis": 0.0, "xpan": 0.0, "b0": "ranking", "b4": "userName", "b2": "r" }, { "b1": "=", "cmd": 15.0, "obsid": "Main", "pos": 83.0, "vis": 1.0, "ms": 0.0, "sel": 0.0, "dis": 0.0, "xpan": 0.0, "b0": "previous", "b2": "point" }, { "b1": "+=", "cmd": 15.0, "obsid": "Main", "pos": 84.0, "vis": 1.0, "ms": 0.0, "sel": 0.0, "dis": 0.0, "xpan": 0.0, "b0": "r", "b2": "1" }, { "b1": "\/$rankingCsvPath$\/", "cmd": 201.0, "obsid": "Main", "pos": 85.0, "vis": 1.0, "ms": 0.0, "sel": 0.0, "dis": 0.0, "xpan": 0.0, "b0": "ranking" }, { "cmd": 141.0, "obsid": "Main", "pos": 86.0, "vis": 1.0, "ms": 0.0, "sel": 0.0, "dis": 0.0, "xpan": 0.0, "b0": "Ranking complete! >>> ranking.csv", "v0": false } ], "press_type": 0.0, "x": 0.75, "border": 2.0, "image": "", "triggers": [ { "on": 0.0, "key": 122.0, "extrakeys": 1.0, "alt": 0.0, "ctrl": 1.0, "group_id": "", "shift": 0.0, "button_id": "IPS_BTN_PRC", "trg": 7.0 } ], "group_id": "", "overlappable": 0.0, "init_variable": "", "deck": 1.0, "width": 0.25, "button_id": "IPS_BTN_PRC", "button_duration": 0.0, "y": 0.5, "switch_deck": "", "height": 0.25, "release_list": [ ], "functions": 81.0, "stretch": 0.0 }